camille/__init__.py
camille/core.cpython-39-darwin.so
camille/lidar.py
camille/output/__init__.py
camille/output/bazefetcher.py
camille/process/__init__.py
camille/process/atm_stb.py
camille/process/delta_temp.py
camille/process/fft.py
camille/process/mooring_fatigue.py
camille/process/pass_filter.py
camille/process/rolling_median.py
camille/source/__init__.py
camille/source/bazefetcher.py
camille/source/windiris.py
camille/source/zephyre.py
camille/util/__init__.py
camille/util/resample.py
camille/util/utcdate.py
camille-1.3.3.dist-info/LICENSE
camille-1.3.3.dist-info/METADATA
camille-1.3.3.dist-info/WHEEL
camille-1.3.3.dist-info/top_level.txt
camille-1.3.3.dist-info/RECORD
