Metadata-Version: 2.1
Name: camille
Version: 1.3.3
Summary: Camille Wind
Home-page: http://github.com/Statoil/camille
Author: Software Innovation Bergen, Equinor ASA
Author-email: fg_gpl@equinor.com
License: UNKNOWN
Platform: UNKNOWN
Requires-Dist: numpy
Requires-Dist: pandas
Requires-Dist: scipy
Requires-Dist: rainflow
Requires-Dist: requests
